[
  {
    "ContainingType": "mmgd.Controllers.mmgdController",
    "Method": "addMessage",
    "RelativePath": "addmessage",
    "HttpMethod": "POST",
    "IsController": true,
    "Order": 0,
    "Parameters": [
      {
        "Name": "data",
        "Type": "mmgd.Controllers.addMessage",
        "IsRequired": true
      }
    ],
    "ReturnTypes": []
  },
  {
    "ContainingType": "mmgd.Controllers.mmgdController",
    "Method": "viewedState",
    "RelativePath": "closenotice",
    "HttpMethod": "POST",
    "IsController": true,
    "Order": 0,
    "Parameters": [
      {
        "Name": "data",
        "Type": "mmgd.Controllers.noticeState",
        "IsRequired": true
      }
    ],
    "ReturnTypes": []
  },
  {
    "ContainingType": "mmgd.Controllers.mmgdController",
    "Method": "LoginCheck",
    "RelativePath": "loginCheck",
    "HttpMethod": "POST",
    "IsController": true,
    "Order": 0,
    "Parameters": [
      {
        "Name": "data",
        "Type": "mmgd.Controllers.searchLoginState",
        "IsRequired": true
      }
    ],
    "ReturnTypes": []
  },
  {
    "ContainingType": "mmgd.Controllers.mmgdController",
    "Method": "membernotice",
    "RelativePath": "notice",
    "HttpMethod": "POST",
    "IsController": true,
    "Order": 0,
    "Parameters": [
      {
        "Name": "data",
        "Type": "mmgd.Controllers.noticeState",
        "IsRequired": true
      }
    ],
    "ReturnTypes": []
  },
  {
    "ContainingType": "mmgd.Controllers.mmgdController",
    "Method": "Test",
    "RelativePath": "test",
    "HttpMethod": "GET",
    "IsController": true,
    "Order": 0,
    "Parameters": [],
    "ReturnTypes": []
  }
]